{"dependencies":[{"name":"D:\\pixijs\\basics\\package.json","includedInParent":true,"mtime":1527055543344},{"name":"pixi.js","loc":{"line":1,"column":22}},{"name":"./01-basics","loc":{"line":3,"column":7}},{"name":"./02-container","loc":{"line":4,"column":7}}],"generated":{"js":"'use strict';\n\nvar _pixi = require('pixi.js');\n\nvar PIXI = _interopRequireWildcard(_pixi);\n\nrequire('./01-basics');\n\nrequire('./02-container');\n\nfunction _interopRequireWildcard(obj) { if (obj && obj.__esModule) { return obj; } else { var newObj = {}; if (obj != null) { for (var key in obj) { if (Object.prototype.hasOwnProperty.call(obj, key)) newObj[key] = obj[key]; } } newObj.default = obj; return newObj; } }","map":{"mappings":[{"generated":{"line":3,"column":0},"source":"index.js","original":{"line":1,"column":0}},{"name":"PIXI","generated":{"line":5,"column":4},"source":"index.js","original":{"line":1,"column":12}},{"generated":{"line":7,"column":0},"source":"index.js","original":{"line":3,"column":0}},{"generated":{"line":9,"column":0},"source":"index.js","original":{"line":4,"column":0}}],"sources":{"index.js":"import * as PIXI from 'pixi.js';\r\n\r\nimport './01-basics';\r\nimport './02-container';\r\n"},"lineCount":null}},"hash":"8e82865ceba75cf3735dc8f080e08a84","cacheData":{"env":{}}}